galaxy_dive/__init__.py
galaxy_dive/config.py
galaxy_dive/analyze_data/__init__.py
galaxy_dive/analyze_data/ahf.py
galaxy_dive/analyze_data/ahf_updater.py
galaxy_dive/analyze_data/generic_data.py
galaxy_dive/analyze_data/gridded_data.py
galaxy_dive/analyze_data/halo_data.py
galaxy_dive/analyze_data/los_data.py
galaxy_dive/analyze_data/particle_data.py
galaxy_dive/analyze_data/simulation_data.py
galaxy_dive/data_management/__init__.py
galaxy_dive/data_management/trove_management.py
galaxy_dive/galaxy_linker/__init__.py
galaxy_dive/galaxy_linker/linker.py
galaxy_dive/plot_data/__init__.py
galaxy_dive/plot_data/ahf.py
galaxy_dive/plot_data/generic_plotter.py
galaxy_dive/plot_data/make_movies.py
galaxy_dive/plot_data/plotting.py
galaxy_dive/plot_data/pu_colormaps.py
galaxy_dive/plot_data/qual_colormaps.py
galaxy_dive/plot_data/scalebar.py
galaxy_dive/read_data/__init__.py
galaxy_dive/read_data/ahf.py
galaxy_dive/read_data/metafile.py
galaxy_dive/read_data/rockstar.py
galaxy_dive/read_data/snapshot.py
galaxy_dive/tests/__init__.py
galaxy_dive/tests/conftest.py
galaxy_dive/tests/test_trends/__init__.py
galaxy_dive/tests/test_trends/test_cgm.py
galaxy_dive/tests/test_trends/test_data_products.py
galaxy_dive/tests/test_utils/__init__.py
galaxy_dive/tests/test_utils/test_astro.py
galaxy_dive/tests/test_utils/test_data_operations.py
galaxy_dive/tests/test_utils/test_hdf5_wrapper.py
galaxy_dive/tests/test_utils/test_mp_utils.py
galaxy_dive/tests/test_utils/test_utilities.py
galaxy_dive/trends/__init__.py
galaxy_dive/trends/cgm.py
galaxy_dive/trends/data_products.py
galaxy_dive/trends/galaxy.py
galaxy_dive/trends/um_smhm.py
galaxy_dive/utils/__init__.py
galaxy_dive/utils/astro.py
galaxy_dive/utils/constants.py
galaxy_dive/utils/data_constants.py
galaxy_dive/utils/data_operations.py
galaxy_dive/utils/executable_helpers.py
galaxy_dive/utils/gen_derived_data_doc.py
galaxy_dive/utils/hdf5_wrapper.py
galaxy_dive/utils/io.py
galaxy_dive/utils/mp_utils.py
galaxy_dive-0.9.3.dist-info/LICENSE
galaxy_dive-0.9.3.dist-info/METADATA
galaxy_dive-0.9.3.dist-info/WHEEL
galaxy_dive-0.9.3.dist-info/top_level.txt
galaxy_dive-0.9.3.dist-info/RECORD
