Metadata-Version: 2.1
Name: galaxy-dive
Version: 0.9.3
Summary: A general analysis suite for hydrodynamic galaxy simulations.
Home-page: https://github.com/zhafen/galaxy-dive
Author: Zach Hafen
Author-email: zachary.h.hafen@gmail.com
License: UNKNOWN
Platform: UNKNOWN
Classifier: License :: OSI Approved :: MIT License
Classifier: Operating System :: OS Independent
Classifier: Programming Language :: Python :: 2.7
Classifier: Programming Language :: Python :: 3
Requires-Dist: pandas (>=0.20.3)
Requires-Dist: mock (>=2.0.0)
Requires-Dist: numpy (>=1.15.4)
Requires-Dist: pytest (>=3.4.0)
Requires-Dist: unyt (>=1.0.4)
Requires-Dist: six (>=1.10.0)
Requires-Dist: setuptools (>=28.8.0)
Requires-Dist: colossus (>=1.2.2)
Requires-Dist: matplotlib (>=2.0.2)
Requires-Dist: h5py (>=2.7.0)
Requires-Dist: numba (>=0.43.1)
Requires-Dist: scipy (>=1.2.1)
Requires-Dist: verdict (>=1.1.3)
